readability_scores/__init__.py
readability_scores/component.py
readability_scores/constants.py
readability_scores-0.1.0.dist-info/LICENSE
readability_scores-0.1.0.dist-info/METADATA
readability_scores-0.1.0.dist-info/WHEEL
readability_scores-0.1.0.dist-info/RECORD
